Workbook

Sheet Customers
A1: customer_id | B1: first_name | C1: last_name | D1: email | E1: phone_number | F1: address | G1: State | H1: postal_code
A2: 288389 | B2: Danielle | C2: Johnson | D2: danielle.johnson@example.com | E2: +1362950628 | F2: 819 Johnson Course, East William, AK 74064 | G2: Illinois | H2: 94351
A3: 231148 | B3: Debra | C3: Gardner | D3: debra.gardner@example.com | E3: +1582334538 | F3: 65423 Garcia Light, West Melanieview, AS 06196 | G3: Washington | H3: 60718
A4: 396922 | B4: Amanda | C4: Dudley | D4: amanda.dudley@example.com | E4: +1184611066 | F4: 310 Kendra Common Apt. 164, Reidstad, GA 49021 | G4: Minnesota | H4: 27961
A5: 716751 | B5: Elizabeth | C5: Miles | D5: elizabeth.miles@example.com | E5: +1795822698 | F5: 327 Nelson Route, Lake Mark, WI 07832 | G5: Iowa | H5: 04708
A6: 69403 | B6: Linda | C6: Morales | D6: linda.morales@example.com | E6: +1326541099 | F6: PSC 9537, Box 6724, APO AE 32826 | G6: West Virginia | H6: 74080
A7: 449245 | B7: Amber | C7: Burgess | D7: amber.burgess@example.com | E7: +1726563708 | F7: 87101 Courtney Turnpike, Carlsonfurt, MS 78605 | G7: New Jersey | H7: 69853
A8: 988210 | B8: John | C8: Tran | D8: john.tran@example.com | E8: +1112327652 | F8: 845 Kelly Estate, Smithview, NY 23917 | G8: North Carolina | H8: 14448
A9: 669987 | B9: Monica | C9: Evans | D9: monica.evans@example.com | E9: +1645098869 | F9: 2880 Burns Creek, Natashaport, IA 08093 | G9: Kansas | H9: 74865
A10: 509597 | B10: Stacey | C10: Miller | D10: stacey.miller@example.com | E10: +1976198296 | F10: 78248 Brandt Plains, Lake Larry, TN 85681 | G10: Mississippi | H10: 57923
A11: 259947 | B11: Rachel | C11: Hayes | D11: rachel.hayes@example.com | E11: +1341266931 | F11: 839 Adrian Station, East Carloston, VI 43810 | G11: California | H11: 67892
A12: 224643 | B12: John | C12: Caldwell | D12: john.caldwell@example.com | E12: +1678998028 | F12: 76311 Gomez Loop Suite 010, Chandlerville, IA 25613 | G12: Illinois | H12: 70793
... A4001: 352676 | B4001: Jordan | C4001: Bowen | D4001: jordan.bowen@example.com | E4001: +1842911788 | F4001: 43399 Jones Gardens Suite 306, New Jeffreymouth, VT 87904 | G4001: Washington | H4001: 61713

Sheet fact_table
A1: fact_id | B1: customer_id | C1: payment_id | D1: driver_id | E1: shipment_id | F1: delivery_id | G1: Sales
A2: =ROW(1:1) -> 1 | B2: =Customers!A2 -> 288389 | C2: =Payments!A2 -> 261600 | D2: =Drivers!A2 -> 509476 | E2: =Shipments!A2 -> 757779 | F2: =Deliveries!A2 -> 64672 | G2: =Deliveries!F2 -> 64.42
A3: =ROW(2:2) -> 2 | B3: =Customers!A3 -> 231148 | C3: =Payments!A3 -> 557068 | D3: =Drivers!A3 -> 387622 | E3: =Shipments!A3 -> 890889 | F3: =Deliveries!A3 -> 961228 | G3: =Deliveries!F3 -> 60.5
A4: =ROW(3:3) -> 3 | B4: =Customers!A4 -> 396922 | C4: =Payments!A4 -> 802730 | D4: =Drivers!A4 -> 814571 | E4: =Shipments!A4 -> 571196 | F4: =Deliveries!A4 -> 702431 | G4: =Deliveries!F4 -> 63.2
A5: =ROW(4:4) -> 4 | B5: =Customers!A5 -> 716751 | C5: =Payments!A5 -> 656274 | D5: =Drivers!A5 -> 114898 | E5: =Shipments!A5 -> 510013 | F5: =Deliveries!A5 -> 966528 | G5: =Deliveries!F5 -> 60.84
A6: =ROW(5:5) -> 5 | B6: =Customers!A6 -> 69403 | C6: =Payments!A6 -> 257584 | D6: =Drivers!A6 -> 182317 | E6: =Shipments!A6 -> 605270 | F6: =Deliveries!A6 -> 944022 | G6: =Deliveries!F6 -> 62.27
A7: =ROW(6:6) -> 6 | B7: =Customers!A7 -> 449245 | C7: =Payments!A7 -> 324561 | D7: =Drivers!A7 -> 740042 | E7: =Shipments!A7 -> 669079 | F7: =Deliveries!A7 -> 141173 | G7: =Deliveries!F7 -> 34.24
A8: =ROW(7:7) -> 7 | B8: =Customers!A8 -> 988210 | C8: =Payments!A8 -> 395517 | D8: =Drivers!A8 -> 189907 | E8: =Shipments!A8 -> 765584 | F8: =Deliveries!A8 -> 592216 | G8: =Deliveries!F8 -> 43.76
A9: =ROW(8:8) -> 8 | B9: =Customers!A9 -> 669987 | C9: =Payments!A9 -> 368008 | D9: =Drivers!A9 -> 316408 | E9: =Shipments!A9 -> 861013 | F9: =Deliveries!A9 -> 408096 | G9: =Deliveries!F9 -> 41.54
A10: =ROW(9:9) -> 9 | B10: =Customers!A10 -> 509597 | C10: =Payments!A10 -> 331567 | D10: =Drivers!A10 -> 408950 | E10: =Shipments!A10 -> 101551 | F10: =Deliveries!A10 -> 774301 | G10: =Deliveries!F10 -> 52.27
A11: =ROW(10:10) -> 10 | B11: =Customers!A11 -> 259947 | C11: =Payments!A11 -> 468930 | D11: =Drivers!A11 -> 803463 | E11: =Shipments!A11 -> 996335 | F11: =Deliveries!A11 -> 705078 | G11: =Deliveries!F11 -> 63.75
A12: =ROW(11:11) -> 11 | B12: =Customers!A12 -> 224643 | C12: =Payments!A12 -> 327717 | D12: =Drivers!A12 -> 214757 | E12: =Shipments!A12 -> 985755 | F12: =Deliveries!A12 -> 514922 | G12: =Deliveries!F12 -> 36.63
A13: =ROW(12:12) -> 12 | B13: =Customers!A13 -> 292075 | C13: =Payments!A13 -> 169822 | D13: =Drivers!A13 -> 374635 | E13: =Shipments!A13 -> 176091 | F13: =Deliveries!A13 -> 436644 | G13: =Deliveries!F13 -> 64.11
A14: =ROW(13:13) -> 13 | B14: =Customers!A14 -> 409386 | C14: =Payments!A14 -> 294523 | D14: =Drivers!A14 -> 487925 | E14: =Shipments!A14 -> 168514 | F14: =Deliveries!A14 -> 638267 | G14: =Deliveries!F14 -> 53.15
A15: =ROW(14:14) -> 14 | B15: =Customers!A15 -> 59942 | C15: =Payments!A15 -> 706358 | D15: =Drivers!A15 -> 639694 | E15: =Shipments!A15 -> 875588 | F15: =Deliveries!A15 -> 986744 | G15: =Deliveries!F15 -> 31.74
A16: =ROW(15:15) -> 15 | B16: =Customers!A16 -> 612024 | C16: =Payments!A16 -> 167751 | D16: =Drivers!A16 -> 855937 | E16: =Shipments!A16 -> 533904 | F16: =Deliveries!A16 -> 152663 | G16: =Deliveries!F16 -> 67.21
A17: =ROW(16:16) -> 16 | B17: =Customers!A17 -> 165409 | C17: =Payments!A17 -> 890425 | D17: =Drivers!A17 -> 98754 | E17: =Shipments!A17 -> 87756 | F17: =Deliveries!A17 -> 574910 | G17: =Deliveries!F17 -> 32.61
A18: =ROW(17:17) -> 17 | B18: =Customers!A18 -> 529959 | C18: =Payments!A18 -> 730697 | D18: =Drivers!A18 -> 443581 | E18: =Shipments!A18 -> 785606 | F18: =Deliveries!A18 -> 912475 | G18: =Deliveries!F18 -> 62.87
A19: =ROW(18:18) -> 18 | B19: =Customers!A19 -> 724586 | C19: =Payments!A19 -> 701154 | D19: =Drivers!A19 -> 901252 | E19: =Shipments!A19 -> 999436 | F19: =Deliveries!A19 -> 51350 | G19: =Deliveries!F19 -> 42.06
A20: =ROW(19:19) -> 19 | B20: =Customers!A20 -> 850155 | C20: =Payments!A20 -> 513131 | D20: =Drivers!A20 -> 589389 | E20: =Shipments!A20 -> 587798 | F20: =Deliveries!A20 -> 488093 | G20: =Deliveries!F20 -> 66.16
A21: =ROW(20:20) -> 20 | B21: =Customers!A21 -> 344207 | C21: =Payments!A21 -> 358145 | D21: =Drivers!A21 -> 497225 | E21: =Shipments!A21 -> 299806 | F21: =Deliveries!A21 -> 960799 | G21: =Deliveries!F21 -> 54.94
A22: =ROW(21:21) -> 21 | B22: =Customers!A22 -> 267095 | C22: =Payments!A22 -> 770201 | D22: =Drivers!A22 -> 524466 | E22: =Shipments!A22 -> 370634 | F22: =Deliveries!A22 -> 393044 | G22: =Deliveries!F22 -> 58.76
A23: =ROW(22:22) -> 22 | B23: =Customers!A23 -> 731076 | C23: =Payments!A23 -> 576004 | D23: =Drivers!A23 -> 498056 | E23: =Shipments!A23 -> 903038 | F23: =Deliveries!A23 -> 224843 | G23: =Deliveries!F23 -> 45.31
A24: =ROW(23:23) -> 23 | B24: =Customers!A24 -> 708446 | C24: =Payments!A24 -> 435575 | D24: =Drivers!A24 -> 529116 | E24: =Shipments!A24 -> 908083 | F24: =Deliveries!A24 -> 15255 | G24: =Deliveries!F24 -> 63.61
A25: =ROW(24:24) -> 24 | B25: =Customers!A25 -> 640967 | C25: =Payments!A25 -> 778082 | D25: =Drivers!A25 -> 408453 | E25: =Shipments!A25 -> 770011 | F25: =Deliveries!A25 -> 970650 | G25: =Deliveries!F25 -> 54.05
A26: =ROW(25:25) -> 25 | B26: =Customers!A26 -> 478634 | C26: =Payments!A26 -> 205169 | D26: =Drivers!A26 -> 130940 | E26: =Shipments!A26 -> 612372 | F26: =Deliveries!A26 -> 246235 | G26: =Deliveries!F26 -> 55.71
A27: =ROW(26:26) -> 26 | B27: =Customers!A27 -> 245884 | C27: =Payments!A27 -> 949450 | D27: =Drivers!A27 -> 791220 | E27: =Shipments!A27 -> 892971 | F27: =Deliveries!A27 -> 539069 | G27: =Deliveries!F27 -> 65.9
A28: =ROW(27:27) -> 27 | B28: =Customers!A28 -> 923435 | C28: =Payments!A28 -> 814666 | D28: =Drivers!A28 -> 277072 | E28: =Shipments!A28 -> 220721 | F28: =Deliveries!A28 -> 579007 | G28: =Deliveries!F28 -> 43.38
A29: =ROW(28:28) -> 28 | B29: =Customers!A29 -> 950983 | C29: =Payments!A29 -> 326895 | D29: =Drivers!A29 -> 613170 | E29: =Shipments!A29 -> 969853 | F29: =Deliveries!A29 -> 124247 | G29: =Deliveries!F29 -> 57.17
A30: =ROW(29:29) -> 29 | B30: =Customers!A30 -> 785408 | C30: =Payments!A30 -> 249200 | D30: =Drivers!A30 -> 758286 | E30: =Shipments!A30 -> 112648 | F30: =Deliveries!A30 -> 90987 | G30: =Deliveries!F30 -> 49.43
A31: =ROW(30:30) -> 30 | B31: =Customers!A31 -> 120096 | C31: =Payments!A31 -> 337358 | D31: =Drivers!A31 -> 569291 | E31: =Shipments!A31 -> 616616 | F31: =Deliveries!A31 -> 612218 | G31: =Deliveries!F31 -> 56.9
A32: =ROW(31:31) -> 31 | B32: =Customers!A32 -> 72306 | C32: =Payments!A32 -> 949165 | D32: =Drivers!A32 -> 955072 | E32: =Shipments!A32 -> 296568 | F32: =Deliveries!A32 -> 748901 | G32: =Deliveries!F32 -> 35.87
A33: =ROW(32:32) -> 32 | B33: =Customers!A33 -> 865845 | C33: =Payments!A33 -> 35691 | D33: =Drivers!A33 -> 50785 | E33: =Shipments!A33 -> 843190 | F33: =Deliveries!A33 -> 633447 | G33: =Deliveries!F33 -> 31.08
A34: =ROW(33:33) -> 33 | B34: =Customers!A34 -> 200337 | C34: =Payments!A34 -> 691764 | D34: =Drivers!A34 -> 842794 | E34: =Shipments!A34 -> 394479 | F34: =Deliveries!A34 -> 246151 | G34: =Deliveries!F34 -> 65.88
A35: =ROW(34:34) -> 34 | B35: =Customers!A35 -> 346859 | C35: =Payments!A35 -> 612614 | D35: =Drivers!A35 -> 541657 | E35: =Shipments!A35 -> 225130 | F35: =Deliveries!A35 -> 681844 | G35: =Deliveries!F35 -> 49.92
A36: =ROW(35:35) -> 35 | B36: =Customers!A36 -> 316950 | C36: =Payments!A36 -> 575531 | D36: =Drivers!A36 -> 817696 | E36: =Shipments!A36 -> 795814 | F36: =Deliveries!A36 -> 564555 | G36: =Deliveries!F36 -> 36.38
A37: =ROW(36:36) -> 36 | B37: =Customers!A37 -> 53872 | C37: =Payments!A37 -> 510116 | D37: =Drivers!A37 -> 619030 | E37: =Shipments!A37 -> 218860 | F37: =Deliveries!A37 -> 342294 | G37: =Deliveries!F37 -> 38.98
A38: =ROW(37:37) -> 37 | B38: =Customers!A38 -> 159097 | C38: =Payments!A38 -> 897354 | D38: =Drivers!A38 -> 86569 | E38: =Shipments!A38 -> 900063 | F38: =Deliveries!A38 -> 563276 | G38: =Deliveries!F38 -> 53.83
A39: =ROW(38:38) -> 38 | B39: =Customers!A39 -> 85131 | C39: =Payments!A39 -> 329129 | D39: =Drivers!A39 -> 576945 | E39: =Shipments!A39 -> 13384 | F39: =Deliveries!A39 -> 404141 | G39: =Deliveries!F39 -> 34.63
A40: =ROW(39:39) -> 39 | B40: =Customers!A40 -> 693300 | C40: =Payments!A40 -> 423487 | D40: =Drivers!A40 -> 353134 | E40: =Shipments!A40 -> 722586 | F40: =Deliveries!A40 -> 368407 | G40: =Deliveries!F40 -> 55.07
A41: =ROW(40:40) -> 40 | B41: =Customers!A41 -> 173982 | C41: =Payments!A41 -> 807870 | D41: =Drivers!A41 -> 107021 | E41: =Shipments!A41 -> 54403 | F41: =Deliveries!A41 -> 32124 | G41: =Deliveries!F41 -> 46.43
A42: =ROW(41:41) -> 41 | B42: =Customers!A42 -> 996971 | C42: =Payments!A42 -> 533929 | D42: =Drivers!A42 -> 530768 | E42: =Shipments!A42 -> 419851 | F42: =Deliveries!A42 -> 31061 | G42: =Deliveries!F42 -> 67.14
A43: =ROW(42:42) -> 42 | B43: =Customers!A43 -> 492841 | C43: =Payments!A43 -> 447310 | D43: =Drivers!A43 -> 504649 | E43: =Shipments!A43 -> 370323 | F43: =Deliveries!A43 -> 722479 | G43: =Deliveries!F43 -> 64.5
A44: =ROW(43:43) -> 43 | B44: =Customers!A44 -> 433321 | C44: =Payments!A44 -> 892047 | D44: =Drivers!A44 -> 304397 | E44: =Shipments!A44 -> 985061 | F44: =Deliveries!A44 -> 568942 | G44: =Deliveries!F44 -> 59.35
A45: =ROW(44:44) -> 44 | B45: =Customers!A45 -> 235615 | C45: =Payments!A45 -> 862956 | D45: =Drivers!A45 -> 257377 | E45: =Shipments!A45 -> 122257 | F45: =Deliveries!A45 -> 598390 | G45: =Deliveries!F45 -> 65.1
A46: =ROW(45:45) -> 45 | B46: =Customers!A46 -> 905997 | C46: =Payments!A46 -> 453659 | D46: =Drivers!A46 -> 395256 | E46: =Shipments!A46 -> 307134 | F46: =Deliveries!A46 -> 149289 | G46: =Deliveries!F46 -> 35.66
A47: =ROW(46:46) -> 46 | B47: =Customers!A47 -> 731380 | C47: =Payments!A47 -> 667479 | D47: =Drivers!A47 -> 983279 | E47: =Shipments!A47 -> 981980 | F47: =Deliveries!A47 -> 187935 | G47: =Deliveries!F47 -> 32.91
A48: =ROW(47:47) -> 47 | B48: =Customers!A48 -> 461694 | C48: =Payments!A48 -> 193757 | D48: =Drivers!A48 -> 939368 | E48: =Shipments!A48 -> 323294 | F48: =Deliveries!A48 -> 293231 | G48: =Deliveries!F48 -> 52.51
A49: =ROW(48:48) -> 48 | B49: =Customers!A49 -> 965664 | C49: =Payments!A49 -> 211725 | D49: =Drivers!A49 -> 452876 | E49: =Shipments!A49 -> 826988 | F49: =Deliveries!A49 -> 20717 | G49: =Deliveries!F49 -> 60.87
A50: =ROW(49:49) -> 49 | B50: =Customers!A50 -> 256059 | C50: =Payments!A50 -> 246214 | D50: =Drivers!A50 -> 960516 | E50: =Shipments!A50 -> 885259 | F50: =Deliveries!A50 -> 286855 | G50: =Deliveries!F50 -> 63.46
A51: =ROW(50:50) -> 50 | B51: =Customers!A51 -> 944986 | C51: =Payments!A51 -> 201998 | D51: =Drivers!A51 -> 760517 | E51: =Shipments!A51 -> 556397 | F51: =Deliveries!A51 -> 116254 | G51: =Deliveries!F51 -> 49.39
A52: =ROW(51:51) -> 51 | B52: =Customers!A52 -> 733247 | C52: =Payments!A52 -> 776055 | D52: =Drivers!A52 -> 930795 | E52: =Shipments!A52 -> 469306 | F52: =Deliveries!A52 -> 253149 | G52: =Deliveries!F52 -> 65.15
A53: =ROW(52:52) -> 52 | B53: =Customers!A53 -> 101883 | C53: =Payments!A53 -> 341239 | D53: =Drivers!A53 -> 668877 | E53: =Shipments!A53 -> 978527 | F53: =Deliveries!A53 -> 629831 | G53: =Deliveries!F53 -> 38.2
A54: =ROW(53:53) -> 53 | B54: =Customers!A54 -> 912677 | C54: =Payments!A54 -> 170768 | D54: =Drivers!A54 -> 130091 | E54: =Shipments!A54 -> 95342 | F54: =Deliveries!A54 -> 876878 | G54: =Deliveries!F54 -> 56
A55: =ROW(54:54) -> 54 | B55: =Customers!A55 -> 26240 | C55: =Payments!A55 -> 968757 | D55: =Drivers!A55 -> 507260 | E55: =Shipments!A55 -> 586742 | F55: =Deliveries!A55 -> 652250 | G55: =Deliveries!F55 -> 39.36
A56: =ROW(55:55) -> 55 | B56: =Customers!A56 -> 779238 | C56: =Payments!A56 -> 346334 | D56: =Drivers!A56 -> 576360 | E56: =Shipments!A56 -> 522092 | F56: =Deliveries!A56 -> 442476 | G56: =Deliveries!F56 -> 40.35
A57: =ROW(56:56) -> 56 | B57: =Customers!A57 -> 427940 | C57: =Payments!A57 -> 350741 | D57: =Drivers!A57 -> 666369 | E57: =Shipments!A57 -> 627530 | F57: =Deliveries!A57 -> 957743 | G57: =Deliveries!F57 -> 67.54
A58: =ROW(57:57) -> 57 | B58: =Customers!A58 -> 22394 | C58: =Payments!A58 -> 778903 | D58: =Drivers!A58 -> 224125 | E58: =Shipments!A58 -> 663383 | F58: =Deliveries!A58 -> 592441 | G58: =Deliveries!F58 -> 40.76
A59: =ROW(58:58) -> 58 | B59: =Customers!A59 -> 693169 | C59: =Payments!A59 -> 610621 | D59: =Drivers!A59 -> 981019 | E59: =Shipments!A59 -> 291763 | F59: =Deliveries!A59 -> 281016 | G59: =Deliveries!F59 -> 54.07
A60: =ROW(59:59) -> 59 | B60: =Customers!A60 -> 909095 | C60: =Payments!A60 -> 492195 | D60: =Drivers!A60 -> 866061 | E60: =Shipments!A60 -> 115385 | F60: =Deliveries!A60 -> 43930 | G60: =Deliveries!F60 -> 60.2
A61: =ROW(60:60) -> 60 | B61: =Customers!A61 -> 399407 | C61: =Payments!A61 -> 378304 | D61: =Drivers!A61 -> 953785 | E61: =Shipments!A61 -> 40609 | F61: =Deliveries!A61 -> 726013 | G61: =Deliveries!F61 -> 32.17
A62: =ROW(61:61) -> 61 | B62: =Customers!A62 -> 267271 | C62: =Payments!A62 -> 968921 | D62: =Drivers!A62 -> 589221 | E62: =Shipments!A62 -> 795875 | F62: =Deliveries!A62 -> 408001 | G62: =Deliveries!F62 -> 51.11
A63: =ROW(62:62) -> 62 | B63: =Customers!A63 -> 136435 | C63: =Payments!A63 -> 681059 | D63: =Drivers!A63 -> 486552 | E63: =Shipments!A63 -> 729638 | F63: =Deliveries!A63 -> 619938 | G63: =Deliveries!F63 -> 59.03
A64: =ROW(63:63) -> 63 | B64: =Customers!A64 -> 886438 | C64: =Payments!A64 -> 101443 | D64: =Drivers!A64 -> 142151 | E64: =Shipments!A64 -> 741476 | F64: =Deliveries!A64 -> 473819 | G64: =Deliveries!F64 -> 40.29
A65: =ROW(64:64) -> 64 | B65: =Customers!A65 -> 776962 | C65: =Payments!A65 -> 849275 | D65: =Drivers!A65 -> 261676 | E65: =Shipments!A65 -> 442243 | F65: =Deliveries!A65 -> 575270 | G65: =Deliveries!F65 -> 63.17
A66: =ROW(65:65) -> 65 | B66: =Customers!A66 -> 89083 | C66: =Payments!A66 -> 895204 | D66: =Drivers!A66 -> 67258 | E66: =Shipments!A66 -> 979899 | F66: =Deliveries!A66 -> 652938 | G66: =Deliveries!F66 -> 46.52
A67: =ROW(66:66) -> 66 | B67: =Customers!A67 -> 510271 | C67: =Payments!A67 -> 546995 | D67: =Drivers!A67 -> 25849 | E67: =Shipments!A67 -> 898669 | F67: =Deliveries!A67 -> 593211 | G67: =Deliveries!F67 -> 53.19
A68: =ROW(67:67) -> 67 | B68: =Customers!A68 -> 398676 | C68: =Payments!A68 -> 192547 | D68: =Drivers!A68 -> 261578 | E68: =Shipments!A68 -> 467360 | F68: =Deliveries!A68 -> 900198 | G68: =Deliveries!F68 -> 42.74
A69: =ROW(68:68) -> 68 | B69: =Customers!A69 -> 92410 | C69: =Payments!A69 -> 793034 | D69: =Drivers!A69 -> 495909 | E69: =Shipments!A69 -> 283223 | F69: =Deliveries!A69 -> 859702 | G69: =Deliveries!F69 -> 50.23
A70: =ROW(69:69) -> 69 | B70: =Customers!A70 -> 813934 | C70: =Payments!A70 -> 102830 | D70: =Drivers!A70 -> 943619 | E70: =Shipments!A70 -> 961524 | F70: =Deliveries!A70 -> 195653 | G70: =Deliveries!F70 -> 49.12
A71: =ROW(70:70) -> 70 | B71: =Customers!A71 -> 591912 | C71: =Payments!A71 -> 799288 | D71: =Drivers!A71 -> 234340 | E71: =Shipments!A71 -> 441046 | F71: =Deliveries!A71 -> 110122 | G71: =Deliveries!F71 -> 61.05
A72: =ROW(71:71) -> 71 | B72: =Customers!A72 -> 675981 | C72: =Payments!A72 -> 626020 | D72: =Drivers!A72 -> 40136 | E72: =Shipments!A72 -> 180746 | F72: =Deliveries!A72 -> 131508 | G72: =Deliveries!F72 -> 53.8
A73: =ROW(72:72) -> 72 | B73: =Customers!A73 -> 460767 | C73: =Payments!A73 -> 607390 | D73: =Drivers!A73 -> 604978 | E73: =Shipments!A73 -> 118212 | F73: =Deliveries!A73 -> 652800 | G73: =Deliveries!F73 -> 37.2
A74: =ROW(73:73) -> 73 | B74: =Customers!A74 -> 950369 | C74: =Payments!A74 -> 505685 | D74: =Drivers!A74 -> 184235 | E74: =Shipments!A74 -> 28500 | F74: =Deliveries!A74 -> 264129 | G74: =Deliveries!F74 -> 67.88
A75: =ROW(74:74) -> 74 | B75: =Customers!A75 -> 379404 | C75: =Payments!A75 -> 186857 | D75: =Drivers!A75 -> 440445 | E75: =Shipments!A75 -> 997598 | F75: =Deliveries!A75 -> 498067 | G75: =Deliveries!F75 -> 49.31
A76: =ROW(75:75) -> 75 | B76: =Customers!A76 -> 170128 | C76: =Payments!A76 -> 277089 | D76: =Drivers!A76 -> 675551 | E76: =Shipments!A76 -> 577781 | F76: =Deliveries!A76 -> 394498 | G76: =Deliveries!F76 -> 63.6
A77: =ROW(76:76) -> 76 | B77: =Customers!A77 -> 947885 | C77: =Payments!A77 -> 634474 | D77: =Drivers!A77 -> 275383 | E77: =Shipments!A77 -> 34841 | F77: =Deliveries!A77 -> 978648 | G77: =Deliveries!F77 -> 69.7
A78: =ROW(77:77) -> 77 | B78: =Customers!A78 -> 800185 | C78: =Payments!A78 -> 687859 | D78: =Drivers!A78 -> 449041 | E78: =Shipments!A78 -> 256936 | F78: =Deliveries!A78 -> 465307 | G78: =Deliveries!F78 -> 42.12
A79: =ROW(78:78) -> 78 | B79: =Customers!A79 -> 681533 | C79: =Payments!A79 -> 37269 | D79: =Drivers!A79 -> 28412 | E79: =Shipments!A79 -> 449819 | F79: =Deliveries!A79 -> 785178 | G79: =Deliveries!F79 -> 58.24
A80: =ROW(79:79) -> 79 | B80: =Customers!A80 -> 249183 | C80: =Payments!A80 -> 886317 | D80: =Drivers!A80 -> 341561 | E80: =Shipments!A80 -> 825203 | F80: =Deliveries!A80 -> 9680 | G80: =Deliveries!F80 -> 34.23
A81: =ROW(80:80) -> 80 | B81: =Customers!A81 -> 696643 | C81: =Payments!A81 -> 649134 | D81: =Drivers!A81 -> 334141 | E81: =Shipments!A81 -> 489482 | F81: =Deliveries!A81 -> 813260 | G81: =Deliveries!F81 -> 30.71
A82: =ROW(81:81) -> 81 | B82: =Customers!A82 -> 793435 | C82: =Payments!A82 -> 343216 | D82: =Drivers!A82 -> 897379 | E82: =Shipments!A82 -> 668729 | F82: =Deliveries!A82 -> 66263 | G82: =Deliveries!F82 -> 43.1
A83: =ROW(82:82) -> 82 | B83: =Customers!A83 -> 569408 | C83: =Payments!A83 -> 595934 | D83: =Drivers!A83 -> 43024 | E83: =Shipments!A83 -> 908371 | F83: =Deliveries!A83 -> 79259 | G83: =Deliveries!F83 -> 43.76
A84: =ROW(83:83) -> 83 | B84: =Customers!A84 -> 544500 | C84: =Payments!A84 -> 395739 | D84: =Drivers!A84 -> 218242 | E84: =Shipments!A84 -> 266340 | F84: =Deliveries!A84 -> 113561 | G84: =Deliveries!F84 -> 53.92
A85: =ROW(84:84) -> 84 | B85: =Customers!A85 -> 456068 | C85: =Payments!A85 -> 25118 | D85: =Drivers!A85 -> 509292 | E85: =Shipments!A85 -> 359556 | F85: =Deliveries!A85 -> 855349 | G85: =Deliveries!F85 -> 35.57
A86: =ROW(85:85) -> 85 | B86: =Customers!A86 -> 634487 | C86: =Payments!A86 -> 171264 | D86: =Drivers!A86 -> 749971 | E86: =Shipments!A86 -> 538925 | F86: =Deliveries!A86 -> 650394 | G86: =Deliveries!F86 -> 53.91
A87: =ROW(86:86) -> 86 | B87: =Customers!A87 -> 224993 | C87: =Payments!A87 -> 546036 | D87: =Drivers!A87 -> 727329 | E87: =Shipments!A87 -> 510333 | F87: =Deliveries!A87 -> 425369 | G87: =Deliveries!F87 -> 65.84
A88: =ROW(87:87) -> 87 | B88: =Customers!A88 -> 235134 | C88: =Payments!A88 -> 39163 | D88: =Drivers!A88 -> 642578 | E88: =Shipments!A88 -> 982903 | F88: =Deliveries!A88 -> 422265 | G88: =Deliveries!F88 -> 62.91
A89: =ROW(88:88) -> 88 | B89: =Customers!A89 -> 417500 | C89: =Payments!A89 -> 578297 | D89: =Drivers!A89 -> 253198 | E89: =Shipments!A89 -> 857095 | F89: =Deliveries!A89 -> 40960 | G89: =Deliveries!F89 -> 55.31
A90: =ROW(89:89) -> 89 | B90: =Customers!A90 -> 169834 | C90: =Payments!A90 -> 844697 | D90: =Drivers!A90 -> 168775 | E90: =Shipments!A90 -> 551909 | F90: =Deliveries!A90 -> 469659 | G90: =Deliveries!F90 -> 30.05
A91: =ROW(90:90) -> 90 | B91: =Customers!A91 -> 287782 | C91: =Payments!A91 -> 434490 | D91: =Drivers!A91 -> 126344 | E91: =Shipments!A91 -> 68377 | F91: =Deliveries!A91 -> 173677 | G91: =Deliveries!F91 -> 51.25
A92: =ROW(91:91) -> 91 | B92: =Customers!A92 -> 277511 | C92: =Payments!A92 -> 751530 | D92: =Drivers!A92 -> 348200 | E92: =Shipments!A92 -> 371146 | F92: =Deliveries!A92 -> 924510 | G92: =Deliveries!F92 -> 46.17
A93: =ROW(92:92) -> 92 | B93: =Customers!A93 -> 150647 | C93: =Payments!A93 -> 881566 | D93: =Drivers!A93 -> 963588 | E93: =Shipments!A93 -> 385461 | F93: =Deliveries!A93 -> 375520 | G93: =Deliveries!F93 -> 30.29
A94: =ROW(93:93) -> 93 | B94: =Customers!A94 -> 907340 | C94: =Payments!A94 -> 500896 | D94: =Drivers!A94 -> 395297 | E94: =Shipments!A94 -> 510723 | F94: =Deliveries!A94 -> 176745 | G94: =Deliveries!F94 -> 35.01
A95: =ROW(94:94) -> 94 | B95: =Customers!A95 -> 493446 | C95: =Payments!A95 -> 898840 | D95: =Drivers!A95 -> 824299 | E95: =Shipments!A95 -> 644977 | F95: =Deliveries!A95 -> 559222 | G95: =Deliveries!F95 -> 45.24
A96: =ROW(95:95) -> 95 | B96: =Customers!A96 -> 653516 | C96: =Payments!A96 -> 272367 | D96: =Drivers!A96 -> 619199 | E96: =Shipments!A96 -> 353049 | F96: =Deliveries!A96 -> 149078 | G96: =Deliveries!F96 -> 69.26
A97: =ROW(96:96) -> 96 | B97: =Customers!A97 -> 156175 | C97: =Payments!A97 -> 26257 | D97: =Drivers!A97 -> 887575 | E97: =Shipments!A97 -> 493142 | F97: =Deliveries!A97 -> 658414 | G97: =Deliveries!F97 -> 42.85
A98: =ROW(97:97) -> 97 | B98: =Customers!A98 -> 314353 | C98: =Payments!A98 -> 965189 | D98: =Drivers!A98 -> 362731 | E98: =Shipments!A98 -> 476994 | F98: =Deliveries!A98 -> 111474 | G98: =Deliveries!F98 -> 33.37
A99: =ROW(98:98) -> 98 | B99: =Customers!A99 -> 734549 | C99: =Payments!A99 -> 28266 | D99: =Drivers!A99 -> 408223 | E99: =Shipments!A99 -> 578574 | F99: =Deliveries!A99 -> 736946 | G99: =Deliveries!F99 -> 60.35
A100: =ROW(99:99) -> 99 | B100: =Customers!A100 -> 956431 | C100: =Payments!A100 -> 122149 | D100: =Drivers!A100 -> 215189 | E100: =Shipments!A100 -> 198660 | F100: =Deliveries!A100 -> 138814 | G100: =Deliveries!F100 -> 45
...

Sheet Drivers
A1: driver_id | B1: first_name | C1: last_name | D1: email | E1: phone_number
A2: 509476 | B2: Eric | C2: Alvarez | D2: eric.alvarez@example.com | E2: 1636712046
A3: 387622 | B3: Catherine | C3: King | D3: catherine.king@example.com | E3: 1324217126
A4: 814571 | B4: Christopher | C4: Villegas | D4: christopher.villegas@example.com | E4: 1102991078
A5: 114898 | B5: James | C5: Gallagher | D5: james.gallagher@example.com | E5: 1762617774
A6: 182317 | B6: Ashley | C6: Nunez | D6: ashley.nunez@example.com | E6: 1104530688
A7: 740042 | B7: Marcia | C7: Ray | D7: marcia.ray@example.com | E7: 1775171763
A8: 189907 | B8: James | C8: Mcmahon | D8: james.mcmahon@example.com | E8: 1898551685
A9: 316408 | B9: Amanda | C9: Johnson | D9: amanda.johnson@example.com | E9: 1305693878
A10: 408950 | B10: Jasmine | C10: Peters | D10: jasmine.peters@example.com | E10: 1382334676
A11: 803463 | B11: Krystal | C11: Nash | D11: krystal.nash@example.com | E11: 1395044815
A12: 214757 | B12: Monica | C12: Price | D12: monica.price@example.com | E12: 1143826806
A13: 374635 | B13: Kathryn | C13: Brown | D13: kathryn.brown@example.com | E13: 1546975113
... A2601: 651004 | B2601: Dawn | C2601: Boone | D2601: dawn.boone@example.com | E2601: 1617312285

Sheet Payments
A1: payment_id | B1: payment_method | C1: payment_amount | D1: payment_date
A2: 261600 | B2: paypal/credit card | C2: 327.33 | D2: 9/8/2023
A3: 557068 | B3: credit card | C3: 286.76 | D3: 11/28/2023
A4: 802730 | B4: credit card | C4: 639.65 | D4: 12/28/2023
A5: 656274 | B5: paypal | C5: 437.39 | D5: 12/15/2023
A6: 257584 | B6: credit card | C6: 217.15 | D6: 12/3/2023
A7: 324561 | B7: credit card | C7: 163.5 | D7: 8/7/2023
A8: 395517 | B8: credit card | C8: 222.38 | D8: 2/27/2023
A9: 368008 | B9: credit card | C9: 463.68 | D9: 1/16/2023
A10: 331567 | B10: cash | C10: 205.76 | D10: 7/20/2023
A11: 468930 | B11: cash | C11: 876.32 | D11: 1/23/2023
A12: 327717 | B12: cash | C12: 225.87 | D12: 8/30/2023
A13: 169822 | B13: cash | C13: 924.62 | D13: 5/15/2023
... A5001: 110226 | B5001: paypal | C5001: 404.25 | D5001: 2/1/2023

Sheet Shipments
A1: shipment_id | B1: item_category | C1: item_name | D1: item_price
A2: 757779 | B2: electronics | C2: Smartphone | D2: 262.91
A3: 890889 | B3: electronics | C3: Tablet | D3: 226.26
A4: 571196 | B4: electronics | C4: Tablet | D4: 576.45
A5: 510013 | B5: furniture | C5: Wardrobe | D5: 376.55
A6: 605270 | B6: book and education | C6: E-Reader | D6: 154.88
A7: 669079 | B7: sports and outdoors | C7: Tent | D7: 129.26
A8: 765584 | B8: book and education | C8: E-Reader | D8: 178.62
A9: 861013 | B9: furniture | C9: Dining Table | D9: 422.14
A10: 101551 | B10: sports and outdoors | C10: Tent | D10: 153.49
A11: 996335 | B11: furniture | C11: Wardrobe | D11: 812.57
A12: 985755 | B12: clothes | C12: T-shirt | D12: 189.24
A13: 176091 | B13: furniture | C13: Chair | D13: 860.51
... A5001: 907704 | B5001: furniture | C5001: Sofa | D5001: 366.01

Sheet Deliveries
A1: delivery_id | B1: order_date | C1: delivery_date | D1: pickup_address | E1: delivery_address | F1: delivery_cost
A2: 64672 | B2: 45177 | C2: 45182 | D2: 700 Martinez Crossroad Suite 380, Leetown, MA 28781 | E2: 018 Lang Circles Suite 699, West Debra, AR 43730 | F2: 64.42
A3: 961228 | B3: 45258 | C3: 45259 | D3: 484 Mendoza Islands Suite 422, East Tina, FL 19065 | E3: 242 Cochran Curve Apt. 784, Lake Steven, WV 60574 | F3: 60.5
A4: 702431 | B4: 45288 | C4: 45290 | D4: 119 Aaron Creek, Port Robert, GU 67779 | E4: 6486 Francis Creek Suite 364, Port Nicholas, NH 41761 | F4: 63.2
A5: 966528 | B5: 45275 | C5: 45280 | D5: 51314 Aguilar Estate, East Tiffany, NY 49879 | E5: 870 Michelle Land, New Angelaburgh, OH 15044 | F5: 60.84
A6: 944022 | B6: 45263 | C6: 45266 | D6: 63262 Kenneth Island, South Daniel, SD 05265 | E6: 3344 Melissa Trail, North Georgeton, CA 29837 | F6: 62.27
A7: 141173 | B7: 45145 | C7: 45147 | D7: 8747 Lawson Landing Suite 843, West Paul, OR 77866 | E7: 922 Stephen Streets, Mcintoshchester, IA 32083 | F7: 34.24
A8: 592216 | B8: 44984 | C8: 44988 | D8: 72530 David Place Suite 643, Josephberg, OH 02653 | E8: 002 George Square, Frankberg, KY 01597 | F8: 43.76
A9: 408096 | B9: 44942 | C9: 44943 | D9: 095 Carrie Plaza Apt. 959, West Nicholasborough, GU 17299 | E9: 1748 Williams Locks, Laurenshire, TX 67614 | F9: 41.54
A10: 774301 | B10: 45122 | C10: 45127 | D10: USCGC Robinson, FPO AP 73295 | E10: 690 Brittany Way Apt. 769, Port Kristinaview, MH 41828 | F10: 52.27
A11: 705078 | B11: 44945 | C11: 44949 | D11: PSC 0599, Box 3423, APO AE 17130 | E11: Unit 2026 Box 9278, DPO AE 89668 | F11: 63.75
A12: 514922 | B12: 45167 | C12: 45168 | D12: 9774 Andrea Club, South Christopher, MI 98571 | E12: 98374 Perez Grove Apt. 126, Karenton, PW 70796 | F12: 36.63
A13: 436644 | B13: 45060 | C13: 45061 | D13: 5245 Rhonda Loaf Suite 201, Lake Zacharyhaven, GA 90508 | E13: 065 David Greens, Port Kayla, FM 23684 | F13: 64.11
... A5001: 822182 | B5001: 44958 | C5001: 44962 | D5001: 3405 Pamela Camp, West Stevenbury, OK 49475 | E5001: 421 Caleb Park Suite 091, Katherinestad, IL 11858 | F5001: 38.24
